{
    "PublishPath":"c:\\publish",
    "SourcePath":"c:\\dev",
    "PublishProfilesPath":"c:\\publish\\_profiles",
    "Sites" : [
        {
            "Name":"affiliate-vendor-api",
            "PublishFolder":"affiliate-vendor-api",
            "SolutionPath":"affiliate-vendor-api\\AffiliateVendorAPI.sln",
            "PublishProfile":"affiliatevendorapi",
            "PublishProfileTargetPath":"C:\\Dev\\affiliate-vendor-api\\Properties\\PublishProfiles"
        },
        {
            "Name":"agency-api",
            "PublishFolder":"agency-api",
            "SolutionPath":"agency-api\\Agency.Api.sln",
            "PublishProfile":"agencyapi",
            "PublishProfileTargetPath":"C:\\Dev\\agency-api\\Agency.Api\\Properties\\PublishProfiles"
        },
        {
            "Name":"client-api",
            "PublishFolder":"client-api",
            "SolutionPath":"client-api\\Client-Api.sln",
            "PublishProfile":"clientapi",
            "PublishProfileTargetPath":"C:\\Dev\\client-api\\Properties\\PublishProfiles"
        },
        {
            "Name":"Corporate",
            "PublishFolder":"corporate",
            "SolutionPath":"corporate\\corporate.sln",
            "PublishProfile":"corporate",
            "PublishProfileTargetPath":"C:\\Dev\\corporate\\My Project\\PublishProfiles"
        },
        {
            "Name":"fs-web-utility",
            "PublishFolder":"fs-web-utility",
            "SolutionPath":"fs-web-utility\\fs-web-utility.sln",
            "PublishProfile":"fswebutility",
            "PublishProfileTargetPath":"C:\\Dev\\fs-web-utility\\FSWebUtility\\My Project\\PublishProfiles"
        },
        {
            "Name":"identity-api",
            "PublishFolder":"identity-api",
            "SolutionPath":"identity-api\\identity.api.sln",
            "PublishProfile":"identityapi",
            "PublishProfileTargetPath":"C:\\Dev\\identity-api\\Properties\\PublishProfiles"
        },
        {
            "Name":"staffing-api",
            "PublishFolder":"staffing-api",
            "SolutionPath":"staffing-api\\staffing-api.sln",
            "PublishProfile":"staffingapi",
            "PublishProfileTargetPath":"C:\\Dev\\staffing-api\\Properties\\PublishProfiles"
        }
    ]
}